{
	"texture_size": [128, 128],
	"textures": {
		"0": "block/portal/wall_dest01",
		"particle": "block/portal/wall_dest01"
	},
	"elements": [
		{
			"from": [3.17187, 0.01562, -16],
			"to": [3.51722, 16, 0],
			"rotation": {"angle": 0, "axis": "y", "origin": [-0.2449, 24.3689, -13.50187]},
			"faces": {
				"north": {"uv": [4.30469, 1.09755, 4.37376, 4.29443], "texture": "#0", "cullface": "north"},
				"east": {"uv": [4.30469, 1.09755, 7.50469, 4.29443], "texture": "#0", "cullface": "north"},
				"south": {"uv": [4.30469, 1.09755, 4.37376, 4.29443], "texture": "#0", "cullface": "north"},
				"west": {"uv": [4.30469, 1.09755, 7.50469, 4.29443], "texture": "#0", "cullface": "north"},
				"up": {"uv": [4.30469, 1.09755, 4.37376, 4.29755], "texture": "#0", "cullface": "north"},
				"down": {"uv": [4.30469, 1.09755, 4.37376, 4.29755], "texture": "#0", "cullface": "north"}
			}
		},
		{
			"from": [3.17187, 15.01562, 0],
			"to": [3.51722, 31, 16],
			"rotation": {"angle": 0, "axis": "y", "origin": [-0.2449, 24.3689, -13.50187]},
			"faces": {
				"north": {"uv": [4.30469, 1.09755, 4.37376, 4.29443], "texture": "#0", "cullface": "north"},
				"east": {"uv": [4.30469, 1.09755, 7.50469, 4.29443], "texture": "#0"},
				"south": {"uv": [4.30469, 1.09755, 4.37376, 4.29443], "texture": "#0", "cullface": "south"},
				"west": {"uv": [4.30469, 1.09755, 7.50469, 4.29443], "texture": "#0"},
				"up": {"uv": [4.30469, 1.09755, 4.37376, 4.29755], "texture": "#0", "cullface": "up"},
				"down": {"uv": [4.30469, 1.09755, 4.37376, 4.29755], "texture": "#0"}
			}
		},
		{
			"from": [1, 0, -16],
			"to": [3, 1, 16.001],
			"faces": {
				"north": {"uv": [5.96875, 11.78113, 6.09375, 12.03113], "rotation": 90, "texture": "#0", "cullface": "north"},
				"east": {"uv": [5.96875, 11.78113, 6.09375, 15.78125], "rotation": 90, "texture": "#0"},
				"south": {"uv": [5.96875, 11.78113, 6.09375, 12.03113], "rotation": 90, "texture": "#0", "cullface": "south"},
				"west": {"uv": [5.96875, 11.78113, 6.09375, 15.78125], "rotation": 90, "texture": "#0"},
				"up": {"uv": [5.96875, 11.78113, 6.21875, 15.78125], "texture": "#0"},
				"down": {"uv": [5.96875, 11.78113, 6.21875, 15.78125], "texture": "#0", "cullface": "down"}
			}
		},
		{
			"from": [2.30469, 0, 7.58789],
			"to": [2.69531, 31.18359, 8.31836],
			"rotation": {"angle": 0, "axis": "y", "origin": [5.52734, 8.26758, 6.37891]},
			"faces": {
				"north": {"uv": [0.25781, 5.39014, 0.30664, 1.49219], "texture": "#0"},
				"east": {"uv": [0.25781, 5.39014, 0.34912, 1.49219], "texture": "#0"},
				"south": {"uv": [0.25781, 5.39014, 0.30664, 1.49219], "texture": "#0"},
				"west": {"uv": [0.25781, 5.39014, 0.34912, 1.49219], "texture": "#0"}
			}
		},
		{
			"from": [2.30469, 0, -8.41211],
			"to": [2.69531, 31.18359, -7.68164],
			"rotation": {"angle": 0, "axis": "y", "origin": [5.52734, 8.26758, 6.37891]},
			"faces": {
				"north": {"uv": [0.25781, 5.39014, 0.30664, 1.49219], "texture": "#0", "cullface": "north"},
				"east": {"uv": [0.25781, 5.39014, 0.34912, 1.49219], "texture": "#0", "cullface": "north"},
				"south": {"uv": [0.25781, 5.39014, 0.30664, 1.49219], "texture": "#0", "cullface": "north"},
				"west": {"uv": [0.25781, 5.39014, 0.34912, 1.49219], "texture": "#0", "cullface": "north"}
			}
		},
		{
			"from": [1, 1, 14.999],
			"to": [3, 31, 16.001],
			"faces": {
				"north": {"uv": [5.49219, 11.69531, 5.74219, 15.44531], "texture": "#0"},
				"east": {"uv": [5.49219, 11.69531, 5.61744, 15.44531], "texture": "#0"},
				"south": {"uv": [5.49219, 11.69531, 5.74219, 15.44531], "texture": "#0", "cullface": "south"},
				"west": {"uv": [5.49219, 11.69531, 5.61744, 15.44531], "texture": "#0"}
			}
		},
		{
			"from": [1, 31, -16],
			"to": [3, 32, 16.001],
			"faces": {
				"north": {"uv": [5.64844, 11.90613, 5.77344, 12.15613], "rotation": 90, "texture": "#0", "cullface": "north"},
				"east": {"uv": [5.48438, 11.67175, 5.60938, 15.67188], "rotation": 90, "texture": "#0", "cullface": "up"},
				"south": {"uv": [5.625, 11.48425, 5.75, 11.73425], "rotation": 90, "texture": "#0", "cullface": "up"},
				"west": {"uv": [5.60156, 11.81238, 5.72656, 15.8125], "rotation": 90, "texture": "#0", "cullface": "up"},
				"up": {"uv": [6, 11.74206, 6.25, 15.74219], "texture": "#0", "cullface": "up"},
				"down": {"uv": [5.46094, 11.78894, 5.71094, 15.78906], "texture": "#0", "cullface": "up"}
			}
		},
		{
			"from": [1, 15.5, -15],
			"to": [3, 16.5, 15.001],
			"faces": {
				"east": {"uv": [5.53125, 12.15613, 5.65625, 15.90625], "rotation": 90, "texture": "#0"},
				"west": {"uv": [5.53125, 12.15613, 5.65625, 15.90625], "rotation": 90, "texture": "#0"},
				"up": {"uv": [5.53125, 12.15613, 5.78125, 15.90625], "texture": "#0", "cullface": "up"},
				"down": {"uv": [5.53125, 12.15613, 5.78125, 15.90625], "texture": "#0"}
			}
		},
		{
			"from": [1, 1, -16],
			"to": [3, 31, -14.998],
			"rotation": {"angle": 0, "axis": "y", "origin": [0, 0, -0.03025]},
			"faces": {
				"north": {"uv": [6.01563, 11.95313, 6.26563, 15.70313], "texture": "#0", "cullface": "north"},
				"east": {"uv": [6.0625, 11.85938, 6.18775, 15.60938], "texture": "#0", "cullface": "north"},
				"south": {"uv": [6.0625, 11.85938, 6.3125, 15.60938], "texture": "#0", "cullface": "north"},
				"west": {"uv": [6.0625, 11.85938, 6.18775, 15.60938], "texture": "#0", "cullface": "north"}
			}
		},
		{
			"from": [2.808, 3.28, 12.71923],
			"to": [3.192, 28.72, 13.00252],
			"rotation": {"angle": 0, "axis": "y", "origin": [1.616, 2.432, 0.00008]},
			"faces": {
				"north": {"uv": [0.17188, 1.36719, 0.21988, 4.54719], "texture": "#0"},
				"east": {"uv": [0.17188, 1.36719, 0.20729, 4.54719], "texture": "#0"},
				"south": {"uv": [0.17188, 1.36719, 0.21988, 4.54719], "texture": "#0"},
				"west": {"uv": [0.17188, 1.36719, 0.20729, 4.54719], "texture": "#0"}
			}
		},
		{
			"from": [2.808, 28.72, -13.00152],
			"to": [3.192, 29.0055, 13.00252],
			"rotation": {"angle": 0, "axis": "y", "origin": [1.616, 2.432, 0.00008]},
			"faces": {
				"north": {"uv": [0.17188, 1.36719, 0.21988, 1.40288], "texture": "#0", "cullface": "north"},
				"east": {"uv": [0.17188, 1.36719, 0.20756, 4.61769], "rotation": 90, "texture": "#0", "cullface": "north"},
				"south": {"uv": [0.17188, 1.36719, 0.21988, 1.40288], "texture": "#0", "cullface": "up"},
				"west": {"uv": [0.17188, 1.36719, 0.20756, 4.61769], "rotation": 90, "texture": "#0", "cullface": "up"},
				"up": {"uv": [0.17188, 1.36719, 0.21988, 4.61769], "texture": "#0", "cullface": "up"},
				"down": {"uv": [0.17188, 1.36719, 0.21988, 4.61769], "texture": "#0", "cullface": "up"}
			}
		},
		{
			"from": [2.808, 3.28, -13.00152],
			"to": [3.192, 28.72, -12.71823],
			"rotation": {"angle": 0, "axis": "y", "origin": [1.616, 2.432, -0.02558]},
			"faces": {
				"north": {"uv": [0.17188, 1.36719, 0.21988, 4.54719], "texture": "#0", "cullface": "north"},
				"east": {"uv": [0.17188, 1.36719, 0.20729, 4.54719], "texture": "#0", "cullface": "north"},
				"south": {"uv": [0.17188, 1.36719, 0.21988, 4.54719], "texture": "#0", "cullface": "north"},
				"west": {"uv": [0.17188, 1.36719, 0.20729, 4.54719], "texture": "#0", "cullface": "north"}
			}
		},
		{
			"from": [2.808, 2.9945, -13.00152],
			"to": [3.192, 3.28, 13.56892],
			"rotation": {"angle": 0, "axis": "y", "origin": [1.616, 2.432, 0.00008]},
			"faces": {
				"north": {"uv": [0.17188, 1.36719, 0.21988, 1.40288], "texture": "#0", "cullface": "north"},
				"east": {"uv": [0.17188, 1.36719, 0.20756, 4.68849], "rotation": 90, "texture": "#0"},
				"south": {"uv": [0.17188, 1.36719, 0.21988, 1.40288], "texture": "#0"},
				"west": {"uv": [0.17188, 1.36719, 0.20756, 4.68849], "rotation": 90, "texture": "#0"},
				"up": {"uv": [0.17188, 1.36719, 0.21988, 4.68849], "texture": "#0"},
				"down": {"uv": [0.17188, 1.36719, 0.21988, 4.68849], "texture": "#0"}
			}
		},
		{
			"from": [1.01563, 1, -0.11912],
			"to": [3.01563, 31, 0.12112],
			"rotation": {"angle": 0, "axis": "y", "origin": [0, 0, -0.00275]},
			"faces": {
				"north": {"uv": [6.01563, 11.95313, 6.26563, 15.70313], "texture": "#0", "cullface": "north"},
				"east": {"uv": [6.0625, 11.85938, 6.09253, 15.60938], "texture": "#0"},
				"south": {"uv": [6.0625, 11.85938, 6.3125, 15.60938], "texture": "#0"},
				"west": {"uv": [6.0625, 11.85938, 6.09253, 15.60938], "texture": "#0"}
			}
		},
		{
			"from": [-7.5839, 1.66056, 8.98833],
			"to": [-7.31827, 6.64806, 15.96875],
			"rotation": {"angle": 45, "axis": "z", "origin": [-1.64099, 9.69723, 13.71875]},
			"faces": {
				"north": {"uv": [14.25489, 14.03478, 14.3213, 15.28166], "texture": "#0"},
				"east": {"uv": [14.25489, 14.03478, 16, 15.28166], "texture": "#0"},
				"south": {"uv": [14.25489, 14.03478, 14.3213, 15.28166], "texture": "#0"},
				"west": {"uv": [14.25489, 14.75313, 16, 16], "texture": "#0", "cullface": "west"},
				"down": {"uv": [14.25489, 14.03478, 14.3213, 15.77989], "texture": "#0", "cullface": "down"}
			}
		},
		{
			"from": [-3.70793, 3.53991, 9.88619],
			"to": [-3.4475, 6.73991, 13.17056],
			"rotation": {"angle": 22.5, "axis": "x", "origin": [-3.30713, 6.33991, 12.16744]},
			"faces": {
				"north": {"uv": [14.25489, 14.03478, 14.32, 14.83478], "texture": "#0", "cullface": "west"},
				"east": {"uv": [14.25489, 14.03478, 15.07599, 14.83478], "texture": "#0", "cullface": "west"},
				"south": {"uv": [14.25489, 14.03478, 14.32, 14.83478], "texture": "#0", "cullface": "west"},
				"west": {"uv": [14.35646, 14.08166, 15.17755, 14.88166], "texture": "#0", "cullface": "west"},
				"up": {"uv": [14.25489, 14.03478, 14.32, 14.85587], "texture": "#0", "cullface": "west"},
				"down": {"uv": [14.25489, 14.03478, 14.32, 14.85587], "texture": "#0", "cullface": "west"}
			}
		},
		{
			"from": [-3.71805, 7.26802, 11.0059],
			"to": [-3.45735, 10.23052, 16.12152],
			"rotation": {"angle": -45, "axis": "x", "origin": [-3.31684, 7.94927, 13.8059]},
			"faces": {
				"north": {"uv": [14.25489, 14.03478, 14.32007, 14.77541], "rotation": 180, "texture": "#0", "cullface": "west"},
				"east": {"uv": [14.25489, 14.03478, 14.99552, 15.31369], "rotation": 270, "texture": "#0", "cullface": "west"},
				"south": {"uv": [14.25489, 14.03478, 14.32007, 14.77541], "texture": "#0", "cullface": "west"},
				"west": {"uv": [14.72109, 14.15197, 16, 14.89259], "texture": "#0", "cullface": "west"},
				"up": {"uv": [14.25489, 14.03478, 14.32007, 15.31369], "rotation": 180, "texture": "#0", "cullface": "west"},
				"down": {"uv": [14.25489, 14.03478, 14.32007, 15.31369], "texture": "#0", "cullface": "west"}
			}
		},
		{
			"from": [-3.69783, 3.33887, 8.98833],
			"to": [-3.4278, 4.62604, 13.83021],
			"rotation": {"angle": 0, "axis": "y", "origin": [-2.88718, -2.26113, 3.4375]},
			"faces": {
				"north": {"uv": [14.25489, 14.03478, 14.3224, 14.35657], "texture": "#0", "cullface": "west"},
				"east": {"uv": [14.25489, 14.03478, 15.46536, 14.35657], "texture": "#0", "cullface": "west"},
				"south": {"uv": [14.25489, 14.03478, 14.3224, 14.35657], "texture": "#0", "cullface": "west"},
				"west": {"uv": [14.27833, 14.45666, 15.4888, 14.77845], "texture": "#0", "cullface": "west"},
				"up": {"uv": [14.25489, 14.03478, 14.3224, 15.24525], "texture": "#0", "cullface": "west"},
				"down": {"uv": [14.25489, 14.03478, 14.3224, 15.24525], "texture": "#0", "cullface": "west"}
			}
		},
		{
			"from": [-3.69783, 4.62604, 12.18833],
			"to": [-3.4278, 7.82604, 13.83021],
			"rotation": {"angle": 0, "axis": "y", "origin": [-2.88718, -2.26113, 3.4375]},
			"faces": {
				"north": {"uv": [14.25489, 14.03478, 14.3224, 14.83478], "texture": "#0", "cullface": "west"},
				"east": {"uv": [14.25489, 14.03478, 14.66536, 14.83478], "texture": "#0", "cullface": "west"},
				"south": {"uv": [14.25489, 14.03478, 14.3224, 14.83478], "texture": "#0", "cullface": "west"},
				"west": {"uv": [15.07521, 13.68322, 15.48568, 14.48322], "texture": "#0", "cullface": "west"},
				"up": {"uv": [14.25489, 14.03478, 14.3224, 14.44525], "texture": "#0", "cullface": "west"}
			}
		},
		{
			"from": [-3.73299, 3.33887, 13.83021],
			"to": [-3.46296, 11.19975, 15.96875],
			"rotation": {"angle": 0, "axis": "y", "origin": [-2.88718, -2.26113, 3.2]},
			"faces": {
				"north": {"uv": [14.25489, 14.03478, 14.3224, 16], "texture": "#0", "cullface": "west"},
				"east": {"uv": [14.25489, 14.03478, 14.78953, 16], "texture": "#0", "cullface": "west"},
				"south": {"uv": [14.25489, 14.03478, 14.3224, 16], "texture": "#0", "cullface": "west"},
				"west": {"uv": [15.46536, 12.83947, 16, 14.80469], "texture": "#0", "cullface": "west"},
				"up": {"uv": [14.25489, 14.03478, 14.3224, 14.56942], "texture": "#0", "cullface": "west"},
				"down": {"uv": [14.25489, 14.03478, 14.3224, 14.56942], "texture": "#0", "cullface": "west"}
			}
		}
	],
	"display": {
		"thirdperson_righthand": {
			"rotation": [1.32, -18.62, 8.05],
			"translation": [0, 2, 0],
			"scale": [0.1, 0.1, 0.1]
		},
		"thirdperson_lefthand": {
			"translation": [0, 0.5, 3.25],
			"scale": [0.4, 0.4, 0.4]
		},
		"firstperson_righthand": {
			"rotation": [180, -2, 180],
			"translation": [15.5, -6, -16.5],
			"scale": [0.3, 0.3, 0.3]
		},
		"firstperson_lefthand": {
			"rotation": [180, 180, 180],
			"translation": [15.5, -6, -11.75],
			"scale": [0.3, 0.3, 0.3]
		},
		"ground": {
			"scale": [0.4, 0.4, 0.4]
		},
		"gui": {
			"rotation": [-180, -90, -180],
			"translation": [-4, -4, 0],
			"scale": [0.5, 0.5, 0.5]
		},
		"head": {
			"rotation": [0, 90, 0],
			"translation": [32, -27.25, -24],
			"scale": [2, 2, 2]
		},
		"fixed": {
			"rotation": [0, 90, 0],
			"translation": [32, 0, -10.074],
			"scale": [2, 2, 2]
		}
	},
	"groups": [
		0,
		1,
		{
			"name": "group",
			"origin": [-0.2449, 24.3689, -13.50187],
			"color": 0,
			"nbt": "{}",
			"armAnimationEnabled": false,
			"children": []
		},
		2,
		3,
		4,
		5,
		6,
		7,
		8,
		9,
		10,
		11,
		12,
		13,
		14,
		15,
		16,
		17,
		18,
		19
	]
}